{
  "VER02201": {
    "Invoice Data": {
      "Buying Entity": "Stamen Gochev",
      "Supplier": "Goldgrube GmbH",
      "Invoice": 25121637,
      "Invoice Date": "2025-12-17T00:00:00"
    },
    "Supplier Data": {
      "Supplier Number": 913019,
      "ISIN": null,
      "Supplier Title": "Veggie Slicer 16in1 Set"
    },
    "Price Data": {
      "Price Net": 5.83,
      "Shipping Net": 0.6,
      "Total Cost Net": 6.43
    },
    "Ebay Category": {
      "Category": "/Haushaltsgeräte/Kleingeräte Küche/Allesschneider & Elektromesser",
      "eBay Category ID": "20681"
    },
    "EAN": {
      "EAN": ""
    },
    "Product Condition": {
      "Condition": "Neu mit Karton"
    },
    "Intern Product Info": {
      "Gender": "",
      "Brand": "Kitchen Ideas",
      "Color": "Grün",
      "Size": ""
    },
    "Intern Generated Info": {
      "More details": "Das Produkt ist ein Gemüseschneider-Set mit 16 Teilen. Es enthält verschiedene Klingen und Zubehörteile für das Schneiden und Reiben von Gemüse. Die Klingen sind scharf und sollten von kleinen Kindern ferngehalten werden.",
      "Keywords": "Gemüseschneider Set Küchenutensilien",
      "Materials": "Kunststoff, Metall"
    },
    "OP": {
      "OP": "15"
    },
    "Status": {
      "Status": "OK"
    },
    "Warehouse": {
      "Lager": "MENZELSTRAßE 10/2/4"
    },
    "Images": {
      "schema_version": "1.0",
      "summary": {
        "has_stock": false,
        "has_phone": true,
        "has_enhanced": false,
        "count_stock": 0,
        "count_phone": 6,
        "count_enhanced": 0,
        "has_main_images": true,
        "count_main_images": 3
      },
      "stock": [],
      "phone": [
        {
          "filename": "VER02201 (1).JPG"
        },
        {
          "filename": "VER02201 (2).jpg"
        },
        {
          "filename": "VER02201 (3).jpg"
        },
        {
          "filename": "VER02201 (4).jpg"
        },
        {
          "filename": "VER02201 (5).JPG"
        },
        {
          "filename": "VER02201 (6).JPG"
        }
      ],
      "enhanced": [],
      "main_images": [
        {
          "filename": "VER02201 (2).jpg"
        },
        {
          "filename": "VER02201 (3).jpg"
        },
        {
          "filename": "VER02201 (6).JPG"
        }
      ],
      "eBay Images": [
        {
          "filename": "VER02201 (2).jpg",
          "order": 1,
          "eBay URL": "https://i.ebayimg.com/00/s/MTYwMFgxNjAw/z/84kAAeSwOn9pqEIR/$_1.JPG?set_id=8800005007"
        },
        {
          "filename": "VER02201 (1).JPG",
          "order": 2,
          "eBay URL": "https://i.ebayimg.com/00/s/MTYwMFgxMjAw/z/D4YAAeSw0y9pqEIX/$_1.JPG?set_id=8800005007"
        },
        {
          "filename": "VER02201 (3).jpg",
          "order": 3,
          "eBay URL": "https://i.ebayimg.com/00/s/MTYwMFgxNjAw/z/mQIAAeSwON5pqEIa/$_1.JPG?set_id=8800005007"
        },
        {
          "filename": "VER02201 (4).jpg",
          "order": 4,
          "eBay URL": "https://i.ebayimg.com/00/s/MTYwMFgxNjAw/z/o7sAAeSwdUVpqEId/$_1.JPG?set_id=8800005007"
        }
      ]
    },
    "eBay Fields": {
      "required": {
        "Modell": "Veggie Slicer"
      },
      "optional": {
        "Marke": "Kitchen Ideas",
        "Stromquelle": "Manuell",
        "Material": "Kunststoff, Metall",
        "Produktart": "Gemüseschneider Set",
        "Farbe": "Grün",
        "Bestandteile inbegriffen": "Klingen, Handprotektor, Reibe, Schaber, Aufbewahrungsbehälter",
        "Leistung": "",
        "Herstellergarantie": "",
        "Herstellernummer": "",
        "Geeignete Lebensmittel": "Gemüse",
        "Besonderheiten": "Multifunktional",
        "Anzahl der Scheiben": "1",
        "Breite": "",
        "Ursprungsland": "",
        "Set enthält": "16 Teile",
        "Anzahl der Bleche": "",
        "Gedeck für": "",
        "Tiefe": "",
        "Höhe": "",
        "Gewicht": "",
        "Klingenlänge": "",
        "Spannung": "",
        "Kabellänge": "",
        "Anzahl der Einheiten": "",
        "Maßeinheit": ""
      }
    },
    "eBay SEO": {
      "Product Type": "Gemüseschneider",
      "Product Model": "",
      "Keyword 1": "Küchenhelfer",
      "Keyword 2": "Gemüse Schneidegerät",
      "Keyword 3": "Gemüseschneider Set"
    },
    "Ebay Listing": {
      "Selling Price Total": "25",
      "Shipping Costs Net": "9.25",
      "Quantity": "1",
      "Condition ID": "1000",
      "Condition Note": "",
      "EAN": "",
      "Modified SKU": "",
      "Schedule Date": "2026-03-13T15:14"
    }
  }
}